{"cameraMode":{"drawMode":0,"name":"Shaded","section":"Shading Mode"},"sceneLighting":true,"audioPlay":false,"sceneViewState":{"m_AlwaysRefresh":false,"showFog":true,"showSkybox":true,"showFlares":true,"showImageEffects":true,"showParticleSystems":true,"showVisualEffectGraphs":true,"m_FxEnabled":true},"in2DMode":false,"pivot":{"x":26.884044647216798,"y":-4.044482231140137,"z":44.09573745727539},"rotation":{"x":-0.20321905612945558,"y":-0.5672867298126221,"z":0.14697609841823579,"w":-0.784425675868988},"size":31.114688873291017,"orthographic":false}